{"m_szDocID":"231643","m_szDocTitle":"Tesla Model X Reservations = ~24,000 (~Twice Model S Reservations Before Production) | CleanTechnica","m_szYear":"2015","m_szDocSumamry":"Tesla Model X Reservations = ~24,000 (~Twice Model S Reservations Before Production) Originally published on EV Obsession . Some serious crowdsourcing by members of the Tesla Motors Club (and, most specifically, Model X reservation holders) and some nice sleuthing by Fred Lambert reveal that there seem to be about twice as many reservations for the Model X as there were for the Model S when production began, 24,000 as compared to 12,000.   There are some obvious reasons for the boost. For one, back when the Model S was launched, Tesla Motors was on shaky grounds and not nearly as many people k","m_szDocBody":"tesla model reservation twice model reservation production originally published obsession crowdsourcing member tesla motor club and specifically model reservation holder nice sleuthing fred lambert reveal reservation model model production began compared obvious reason boost one back model launched tesla motor shaky ground people knew company faith product faith survival all year later tesla practically hottest company world vehicle the model won car award book called car century car driver vehicle level rest car market model bring appeal women reportedly ability tow extra interior space insanely cool falconwing door allwheel drive which model didnt initially have bigger appeal suvs people desire now emphasise reservation data official tesla data member tesla motor club tmc gathering reservation data model tesla unveiled prototype member post sequence number region version vehicle signature regular production summary tally highest number reported date regularly updated show current tally total fred write funny thing fred note tesla hasnt shown official final version model final base price elon musk stated conference call month ago tesla wouldnt unveiling model delivery began special feature apparently hold surprise course assumed initial reservation holder full detail sneak peek order finalise order tesla model reservationholder configure vehicle finalise order end month related cleantechnicas completely free electric car report electric car early adopter follower want youd attend electric vehicle solar power event conducted cleantechnica date hottest cleantech new subscribing free cleantech newsletter eye sectorspecific new also free solar energy newsletter electric vehicle newsletter wind energy newsletter tag tesla model tesla model tesla model reservation zachary shahan tryin and specy letter time spend time cleantechnica director chief editor otherwise enthusiastically fulfilling duty obsession gas solar love planetsave bikocity president important media zach recognised globally solar energy electric car energy storage wind energy expert speak related conference event connect social media zacharyshahancom related post dag johansen nice pipeline vehicle build revenue gigafactory developed gigafactory key push battery price hit tipping point keanwood gigafactory overstated importance ive heard tesla pay reduction take price evs unstoppable subsidy needed all zachary shahan writing tesla fighter doesnt get battery supply compete tesla never mind huge quality advantage tesla has chem scaling production capacity supplying automaker split dozen model model tesla fighter lot scene havent word yet steve grinwis thought chem capable building battery pack year plant state gigafactory sneeze chem scale volt leaf off green leaf great range expect zachary shahan yeah chem supply battery most evs market split battery model steve grinwis arent evs selling large number leaf volt though imiev pretty flop smart love selling year guess well chem plant germany chem plant capable providing sell meet current tesla production started gigafactory cool make doubt battery plant space dont lot space now arent ramping production year mitsubishi outlander phev teach manufacturer supply side constrained battery zachary shahan piece lining evs battery producer line dozen now largest number chem zoe kangoo sale region neroden byd produce battery dont sell autos only buse worth taking chinese market occasionally speaking which batteryelectric bus manufacturer china batteryelectric bus market crowded love list manufacturer offgridman thought top zach multiple manufacturer supplied hundred thousand size number cell needed current volt leaf model increasing year next upcoming bolt higher total pack production number decrease higher number cell needed upcoming model zachary shahan good point chem samsung sdi plan underway hugely ramp production see automaker battery battery manufacturer produce nrgall top wont gigafactory producing cell power wall zachary shahan yeah take time increase production capacity chem strong signal basically imagine happen year tesla minimum steve grinwis chem plant michigan doubling workforce again gigafactory pretty significant ","m_szGeo1":"United States","m_szSourceType":"source_industry","m_szSrcUrl":"http://cleantechnica.com/2015/07/02/tesla-model-x-reservations-24000-twice-model-s-reservations-before-production/","m_Places":["Tesla","Us","Split","The States","Well","Germany","China","Michigan"],"m_People":["Fred Lambert","Elon Musk","Zachary Shahan","Dag Johansen","Steve Grinwis","Zoe","Kangoo Ze"],"m_Companies":["Tesla Motors","Lg Chem","Volt","Guess","I3","Ramping","Samsung Sdi"],"m_BiGrams":["zachary shahan","tesla model","model reservation","tesla motor","model tesla","electric car","steve grinwis","chem plant"],"m_TriGrams":[],"m_SocialTags":[],"m_Topics":[],"m_Industry":[],"m_Technology":[],"m_BiCnt":[6,5,4,3,3,3,3,3],"m_TriCnt":[],"m_iDocBodyWordCnt":587}
