{"m_szDocID":"233572","m_szDocTitle":"To Lease or To Own: Simplified Solar Calculator | CleanTechnica","m_szYear":"2016","m_szDocSumamry":"To Lease or To Own: Simplified Solar Calculator February 16th, 2016 by John Farrell   Originally published on  ilsr.org . Now simplified, a new solar loan vs lease calculator is here. This tool has been featured on National Public Radio for its ability to help consumers make smart solar system decisions. Just enter in your zip code, electric utility, and solar array size. Then set the terms of your loan or lease to see how solar ownership stacks up against third-party options. Purchase (cash): Customer owns the PV system from day one, pays upfront with cash. Purchase (loan): Customer owns the ","m_szDocBody":"own simplified solar calculator john farrell originally publishedon ilsrorg simplified anew solar loan calculator here thistool featured national public radio ability consumer make smart solar system decision enter zip code electric utility solar array size set term loan solar ownership stack thirdparty option purchase cashcustomer own system day one pay upfront cash purchase loancustomer own system starting day purchased loan downpayment paid back fixed interest rate lease year buyoutinstall company developer own system customer pay fixed monthly payment adjusted inflation year customer elect purchase system assume full ownership lease extensionsame lease year buyout year customer elect extend leasing company assumed cost watt federal itc note utility data based residential rate eia form electric utility rate date note insolation rate zip code gleaned national renewable energy laboratory data fun prepared complex solar calculator meant data mushing due outsoon timely update follow john farrell democratic energy weekly update cleantechnicas completely free electric car report electric car early adopter follower want youd attend electric vehicle solar power event conducted cleantechnica date hottest cleantech new subscribing free cleantech newsletter eye sectorspecific new also free solar energy newsletter electric vehicle newsletter wind energy newsletter tag nrel rooftop solar calculator solar calculator vote solar john farrell direct democratic energy programme ilsr focuse energy policy development expand benefit local ownership dispersed generation renewable energy seminal paper democratising electricity system describe blast roadblock distributed renewable energy generation smallscale renewable energy project key biggest stride renewable energy development farrell authored landmark report energy selfreliant state serve definitive energy atlas united state detailing statebystate renewable electricity generation potential farrell regularly discussion analysis distributed renewable energy policy blog energy selfreliant state energyselfreliantstatesorg article regularly syndicated grist renewable energy world john farrell found related post tax credit extension impact renewable deployment electricity emission aok simplified kind rudimentary calculation srec incentive swing pendulum farther showing purchase decision hate part remotely consideration juxxr lol wuestenblitz variable solar simple calculator suffice roof orientation shading time person home etc unobstructed southern facing roof tax liability plan home long term mean buy system roof space northern facing heavily shaded roof power rate utility jameswimberley calculator appear leave orientation tilt good estimate annual output pvwatt aok true estimate output accurately equal comparison doesnt matter here wildisreal dont pay federal income taxe arent planning selling home year make sense put squarely minority course purchase solar system folk home lease made sense system expensive massive incentive needed carried day passed newnodm dont tax deduction interest system purchased home equity loan also lease common they ppa buy loan common comparison stuff dont intend life aint solar marion mead qualify hero programme credit cheque there payment tacked property tax shop solar company local company good bbb rating preferable hero programme recommend one company shopping deal make worth while give option comparison calculator tally spreadsheet comparison wildisreal pretty hardcore marion respect everyone time suggest add dont hear martam minute time company save that take hour worth time wildisreal proper solar sale experience take longer minute but based comment shady quickbuck operation there fair enough gco take couple minute good run away dont remember installer contacted site time measure dimension shading etc discuss option proposal made sense similar other claiming rely hightech sat image missing skylight completely rocker difference professional smoothtalking technicallyilliterate salesperson selling lead absolutely stay ivor oconnor company honest matt ","m_szGeo1":"United States","m_szSourceType":"source_industry","m_szSrcUrl":"http://cleantechnica.com/2016/02/16/lease-simplified-solar-calculator/","m_Places":["U.s.","United States"],"m_People":["John Farrell","Marion Meads","Ivor O’connor"],"m_Companies":["National Public Radio","Itc","Us National Renewable Energy Laboratory","Twitter","Hero","Bbb"],"m_BiGrams":["renewable energy","solar calculator","john farrell","own system"],"m_TriGrams":[],"m_SocialTags":[],"m_Topics":[],"m_Industry":[],"m_Technology":[],"m_BiCnt":[7,4,4,3],"m_TriCnt":[],"m_iDocBodyWordCnt":548}
